LICENSE
MANIFEST.in
README.md
setup.py
django_jingo_offline_compressor.egg-info/PKG-INFO
django_jingo_offline_compressor.egg-info/SOURCES.txt
django_jingo_offline_compressor.egg-info/dependency_links.txt
django_jingo_offline_compressor.egg-info/not-zip-safe
django_jingo_offline_compressor.egg-info/top_level.txt
jingo_offline_compressor/__init__.py
jingo_offline_compressor/jinja2ext.py
jingo_offline_compressor/models.py
jingo_offline_compressor/test_settings.py
jingo_offline_compressor/management/__init__.py
jingo_offline_compressor/management/commands/__init__.py
jingo_offline_compressor/management/commands/compress_jingo.py
jingo_offline_compressor/management/commands/compress_jingo_0.py
jingo_offline_compressor/tests/__init__.py